apknife/__init__.py
apknife/apknife.py
apknife/modules/__init__.py
apknife/modules/analyzer.py
apknife/modules/api_finder.py
apknife/modules/apk_modifier.py
apknife/modules/builder.py
apknife/modules/catch_rat.py
apknife/modules/dex_extractor.py
apknife/modules/extract_sensitive.py
apknife/modules/extractor.py
apknife/modules/interactive_mode.py
apknife/modules/java_extractor.py
apknife/modules/manifest_decoder.py
apknife/modules/manifest_editor.py
apknife/modules/permission_scanner.py
apknife/modules/protection_scanner.py
apknife/modules/signer.py
apknife/modules/smali_tools.py
apknife/modules/vulnerability_scanner.py
apknife/modules/tools/baksmali.jar
apknife-1.2.0.dist-info/LICENSE
apknife-1.2.0.dist-info/METADATA
apknife-1.2.0.dist-info/WHEEL
apknife-1.2.0.dist-info/entry_points.txt
apknife-1.2.0.dist-info/top_level.txt
apknife-1.2.0.dist-info/RECORD
