Metadata-Version: 2.2
Name: apknife
Version: 1.2.0
Summary: APKnife is an advanced tool for APK analysis, modification, and security auditing. Whether you're a security researcher, penetration tester, or Android developer, APKnife provides powerful features for reverse engineering, decompiling, modifying, and analyzing APK files.
Home-page: https://github.com/elrashedy1992/APKnife
Author: Mr_nightmare
Author-email: Mr_nightmare <hmjany18@gmail.com>
License: MIT
Project-URL: Homepage, https://github.com/elrashedy1992/APKnife
Project-URL: Documentation, https://github.com/elrashedy1992/APKnife/wiki
Project-URL: Source, https://github.com/elrashedy1992/APKnife
Requires-Python: >=3.6
License-File: LICENSE
Requires-Dist: androguard==4.1.3
Requires-Dist: defusedxml==0.7.1
Requires-Dist: lxml==5.3.1
Requires-Dist: Pillow==11.1.0
Requires-Dist: prompt_toolkit==3.0.50
Requires-Dist: requests==2.32.3
Requires-Dist: setuptools==75.8.2
Requires-Dist: tqdm==4.67.1
Dynamic: author
Dynamic: home-page
Dynamic: requires-python
